cspy-1.0.3.dist-info/RECORD
cspy-1.0.3.dist-info/WHEEL
cspy-1.0.3.dist-info/top_level.txt
cspy-1.0.3.dist-info/METADATA
cspy/__init__.py
cspy/checking.py
cspy/preprocessing.py
cspy/algorithms/pyBiDirectionalCpp.py
cspy/algorithms/_pyBiDirectionalCpp.so
cspy/algorithms/grasp.py
cspy/algorithms/__init__.py
cspy/algorithms/bidirectional.py
cspy/algorithms/path_base.py
cspy/algorithms/greedy_elimination.py
cspy/algorithms/psolgent.py
cspy/algorithms/tabu.py
cspy/.libs/libBiDirectionalCpp.1.0.3.dylib
