Metadata-Version: 2.1
Name: cspy
Version: 1.0.3
Summary: (Resource) Constrained  Shortest Path algorithms in Python
Home-page: https://github.com/torressa/cspy
Author: torressa
Author-email: "David Torres" <david.sanchez@sintef.no>
License: UNKNOWN
Platform: UNKNOWN
Classifier: Operating System :: POSIX :: Linux
Classifier: Operating System :: MacOS :: MacOS X
Classifier: Operating System :: Microsoft :: Windows
Classifier: Programming Language :: Python
Classifier: Programming Language :: Python :: 3.6
Classifier: Programming Language :: Python :: 3.7
Classifier: Programming Language :: Python :: 3.8
Classifier: Programming Language :: Python :: 3.9
Classifier: Programming Language :: C++
Requires-Dist: networkx
Requires-Dist: numpy
